roadtrip_tools/__init__.py
roadtrip_tools/concurrency.py
roadtrip_tools/config.py
roadtrip_tools/data/.gitkeep
roadtrip_tools/data/__init__.py
roadtrip_tools/data/google_cloud.py
roadtrip_tools/data/make_dataset.py
roadtrip_tools/data/nrel_api.py
roadtrip_tools/data/plugshare.py
roadtrip_tools/features/.gitkeep
roadtrip_tools/features/__init__.py
roadtrip_tools/features/build_features.py
roadtrip_tools/logs.py
roadtrip_tools/models/.gitkeep
roadtrip_tools/models/__init__.py
roadtrip_tools/models/openai_tools.py
roadtrip_tools/models/predict_model.py
roadtrip_tools/models/train_model.py
roadtrip_tools/visualization/.gitkeep
roadtrip_tools/visualization/__init__.py
roadtrip_tools/visualization/visualize.py
roadtrip_tools-0.1.1.dist-info/LICENSE
roadtrip_tools-0.1.1.dist-info/METADATA
roadtrip_tools-0.1.1.dist-info/WHEEL
roadtrip_tools-0.1.1.dist-info/RECORD
