Metadata-Version: 2.1
Name: roadtrip-tools
Version: 0.1.1
Summary: Generally useful tools built for AI-enabled EV navigation
Author: Dave Rench McCauley
Author-email: dave@getroadtrip.ai
Requires-Python: >=3.11,<4.0
Classifier: Programming Language :: Python :: 3
Classifier: Programming Language :: Python :: 3.11
Classifier: Programming Language :: Python :: 3.12
Requires-Dist: beautifulsoup4 (>=4.12.3,<5.0.0)
Requires-Dist: chardet (>=5.2.0,<6.0.0)
Requires-Dist: click (>=8.1.7,<9.0.0)
Requires-Dist: coverage (>=7.3.3,<8.0.0)
Requires-Dist: cython (>=3.0.10,<4.0.0)
Requires-Dist: db-dtypes (>=1.2.0,<2.0.0)
Requires-Dist: flake8 (>=6.1.0,<7.0.0)
Requires-Dist: geodatasets (>=2024.7.0,<2025.0.0)
Requires-Dist: geopandas (>=1.0.1,<2.0.0)
Requires-Dist: google-cloud-bigquery (>=3.25.0,<4.0.0)
Requires-Dist: google-cloud-logging (>=3.11.1,<4.0.0)
Requires-Dist: google-cloud-storage (>=2.17.0,<3.0.0)
Requires-Dist: h3pandas (>=0.2.6,<0.3.0)
Requires-Dist: ipykernel (>=6.29.0,<7.0.0)
Requires-Dist: ipywidgets (>=8.1.3,<9.0.0)
Requires-Dist: joblib (>=1.4.2,<2.0.0)
Requires-Dist: matplotlib (>=3.9.0,<4.0.0)
Requires-Dist: nest-asyncio (>=1.6.0,<2.0.0)
Requires-Dist: openai (>=1.6.0,<2.0.0)
Requires-Dist: pandas (>=2.1.4,<3.0.0)
Requires-Dist: pillow (>=10.1.0,<11.0.0)
Requires-Dist: protobuf (>=4.0.0,<5.0.0)
Requires-Dist: pypdf (>=4.0.0,<5.0.0)
Requires-Dist: pyproj (>=3.6.1,<4.0.0)
Requires-Dist: pytest (>=8.2.2,<9.0.0)
Requires-Dist: python-dotenv
Requires-Dist: ray[default] (>=2.31.0,<3.0.0)
Requires-Dist: rich (>=13.7.0,<14.0.0)
Requires-Dist: selenium (>=4.21.0,<5.0.0)
Requires-Dist: selenium-wire-2 (>=0.2.1,<0.3.0)
Requires-Dist: sphinx (>=7.2.6,<8.0.0)
Requires-Dist: tenacity (>=8.5.0,<9.0.0)
